gzy_mcp_demo_add_two_numbers/__init__.py
gzy_mcp_demo_add_two_numbers-0.1.0.dist-info/METADATA
gzy_mcp_demo_add_two_numbers-0.1.0.dist-info/WHEEL
gzy_mcp_demo_add_two_numbers-0.1.0.dist-info/entry_points.txt
gzy_mcp_demo_add_two_numbers-0.1.0.dist-info/RECORD
