Metadata-Version: 2.4
Name: gzy-mcp-demo-add-two-numbers
Version: 0.1.0
Summary: Add your description here
Author-email: guoziyangnb <2263831821@qq.com>
Requires-Python: >=3.13
Requires-Dist: mcp[cli]>=1.11.0
